geoffrey_cheesecake-0.0.1.dist-info/DESCRIPTION.rst
geoffrey_cheesecake-0.0.1.dist-info/RECORD
geoffrey_cheesecake-0.0.1.dist-info/WHEEL
geoffrey_cheesecake-0.0.1.dist-info/top_level.txt
geoffrey_cheesecake-0.0.1.dist-info/metadata.json
geoffrey_cheesecake-0.0.1.dist-info/METADATA
geoffreyplugins/__init__.py
geoffreyplugins/cheesecake.py
geoffreyplugins/cheesecake/main.js
geoffreyplugins/cheesecake/assets/.gitkeep
