Metadata-Version: 2.0
Name: geoffrey-cheesecake
Version: 0.0.1
Summary: rank Python packages based on various empirical "kwalitee" factors
Home-page: https://github.com/GeoffreyCI/geoffrey-cheesecake
Author: Miguel Reguero Bejar
Author-email: mreguerob0@gmail.com
License: UNKNOWN
Platform: UNKNOWN
